loam_ai/__init__.py
loam_ai/cli.py
loam_ai/client.py
loam_ai/models.py
loam_ai/py.typed
loam_ai-0.1.1.dist-info/METADATA
loam_ai-0.1.1.dist-info/WHEEL
loam_ai-0.1.1.dist-info/entry_points.txt
loam_ai-0.1.1.dist-info/licenses/LICENSE
loam_ai-0.1.1.dist-info/RECORD
