Metadata-Version: 2.4
Name: loam-ai
Version: 0.1.1
Summary: CLI tool for AWS Bedrock model invocation
Project-URL: Homepage, https://github.com/nulib-labs/loam-ai
Project-URL: Repository, https://github.com/nulib-labs/loam-ai.git
Project-URL: Issues, https://github.com/nulib-labs/loam-ai/issues
Author: Brendan Quinn
License-Expression: MIT
License-File: LICENSE
Keywords: ai,aws,bedrock,cli,machine-learning
Classifier: Development Status :: 4 - Beta
Classifier: Environment :: Console
Classifier: Intended Audience :: Developers
Classifier: License :: OSI Approved :: MIT License
Classifier: Programming Language :: Python :: 3
Classifier: Programming Language :: Python :: 3.10
Classifier: Topic :: Software Development :: Libraries :: Python Modules
Requires-Python: >=3.10
Requires-Dist: boto3>=1.34.0
Requires-Dist: click>=8.1.0
Requires-Dist: rich>=13.0.0
